RubAmin/Socket.py
RubAmin/__init__.py
RubAmin/connections.py
RubAmin/createMethod.py
RubAmin/encryption.py
RubAmin/login.py
RubAmin/media.py
RubAmin/rubika.py
RubAmin/rubino.py
RubAmin/socket__init__.py
RubAmin/tools.py
rubamin-0.1.4.dist-info/LICENSE
rubamin-0.1.4.dist-info/METADATA
rubamin-0.1.4.dist-info/WHEEL
rubamin-0.1.4.dist-info/top_level.txt
rubamin-0.1.4.dist-info/RECORD
